asyncio_tools.py
asyncio_tools-1.0.0.data/data/py.typed
asyncio_tools-1.0.0.dist-info/LICENSE
asyncio_tools-1.0.0.dist-info/METADATA
asyncio_tools-1.0.0.dist-info/WHEEL
asyncio_tools-1.0.0.dist-info/top_level.txt
asyncio_tools-1.0.0.dist-info/RECORD
