Metadata-Version: 2.1
Name: asyncio-tools
Version: 1.0.0
Summary: Useful utilities for working with asyncio.
Home-page: https://github.com/piccolo-orm/asyncio_tools
Author: Daniel Townsend
Author-email: dan@dantownsend.co.uk
License: MIT
Classifier: License :: OSI Approved :: MIT License
Classifier: Programming Language :: Python
Classifier: Programming Language :: Python :: 3
Classifier: Programming Language :: Python :: 3.8
Classifier: Programming Language :: Python :: 3.9
Classifier: Programming Language :: Python :: 3.10
Classifier: Programming Language :: Python :: Implementation :: CPython
Requires-Python: >=3.8.0
License-File: LICENSE
